<?xml version="1.0" encoding="utf-8" ?><dwsync><file name="telegram-chat.js" server="208.97.137.141//home/totalpat_ftp/totalpat.com/wp-content/plugins/" local="3550459844" remote="16435361732" Dst="-1" /><file name="jquery.transit.min.js" server="208.97.137.141//home/totalpat_ftp/totalpat.com/wp-content/plugins/" local="3550264558" remote="16435169145" Dst="-1" /><file name="telegram-functions.js" server="208.97.137.141//home/totalpat_ftp/totalpat.com/wp-content/plugins/" local="3550459828" remote="16435361721" Dst="-1" /><file name="telegram-functions.js" server="208.97.137.141//home/totalpat_ftp/waempresarial.com/wp-content/plugins/" local="3551988518" remote="16436890408" Dst="-1" /><file name="telegram-chat.js" server="208.97.137.141//home/totalpat_ftp/waempresarial.com/wp-content/plugins/" local="3552094879" remote="16436996772" Dst="-1" /><file name="telegram-functions.js" server="creapix.com.mx/wp-content/plugins/" local="3551635829" remote="16436541288" Dst="-1" /><file name="telegram-chat.js" server="creapix.com.mx/wp-content/plugins/" local="3551635832" remote="16436541288" Dst="-1" /><file name="jquery.transit.min.js" server="208.97.137.141//home/totalpat_ftp/waempresarial.com/wp-content/plugins/" local="3550264558" remote="12141570599" Dst="-1" /><file name="telegram-functions.js" server="daxpro.lat/wp-content/plugins/" local="3551654408" remote="16436559888" Dst="-1" /><file name="telegram-chat.js" server="daxpro.lat/wp-content/plugins/" local="3551654483" remote="16436559948" Dst="-1" /><file name="telegram-chat.js" server="taali.com.mx/wp-content/plugins/" local="3552094864" remote="16437000348" Dst="-1" /><file name="telegram-chat.js" server="totalpat.com/waempresarial.com/wp-content/plugins/" local="3553199803" remote="320909690643515072" Dst="-1" /><file name="telegram-functions.js" server="totalpat.com/waempresarial.com/wp-content/plugins/" local="3552503753" remote="320892098456774602" Dst="-1" /><file name="telegram-functions.js" server="waempresarial.com/waempresarial.com/wp-content/plugins/" local="3562520244" remote="320944875024999902" Dst="-1" /><file name="telegram-chat.js" server="waempresarial.com/waempresarial.com/wp-content/plugins/" local="3562592582" remote="320944875024999901" Dst="-1" /><file name="jquery.transit.min.js" server="waempresarial.com/waempresarial.com/wp-content/plugins/" local="3550264558" remote="320944875024999882" Dst="-1" /></dwsync>